[
    {
        "Name": "Leanne Graham",
        "Email": "Sincere@april.biz",
        "Company": "Romaguera-Crona",
        "City": "Gwenborough",
        "Potential_Relationship": false
    },
    {
        "Name": "Ervin Howell",
        "Email": "Shanna@melissa.tv",
        "Company": "Deckow-Crist",
        "City": "Wisokyburgh",
        "Potential_Relationship": false
    },
    {
        "Name": "Clementine Bauch",
        "Email": "Nathan@yesenia.net",
        "Company": "Romaguera-Jacobson",
        "City": "McKenziehaven",
        "Potential_Relationship": false
    },
    {
        "Name": "Patricia Lebsack",
        "Email": "Julianne.OConner@kory.org",
        "Company": "Robel-Corkery",
        "City": "South Elvis",
        "Potential_Relationship": false
    },
    {
        "Name": "Chelsey Dietrich",
        "Email": "Lucio_Hettinger@annie.ca",
        "Company": "Keebler LLC",
        "City": "Roscoeview",
        "Potential_Relationship": false
    },
    {
        "Name": "Mrs. Dennis Schulist",
        "Email": "Karley_Dach@jasper.info",
        "Company": "Considine-Lockman",
        "City": "South Christy",
        "Potential_Relationship": false
    },
    {
        "Name": "Kurtis Weissnat",
        "Email": "Telly.Hoeger@billy.biz",
        "Company": "Johns Group",
        "City": "Howemouth",
        "Potential_Relationship": false
    },
    {
        "Name": "Nicholas Runolfsdottir V",
        "Email": "Sherwood@rosamond.me",
        "Company": "Abernathy Group",
        "City": "Aliyaview",
        "Potential_Relationship": false
    },
    {
        "Name": "Glenna Reichert",
        "Email": "Chaim_McDermott@dana.io",
        "Company": "Yost and Sons",
        "City": "Bartholomebury",
        "Potential_Relationship": false
    },
    {
        "Name": "Clementina DuBuque",
        "Email": "Rey.Padberg@karina.biz",
        "Company": "Hoeger LLC",
        "City": "Lebsackbury",
        "Potential_Relationship": false
    }
]